{
    "Disease 1": "-",
    "Disease 2": "(MMR) Measles / Mumps / Rubella",
    "Keyword": "",
    "Master Answer": "For all individuals born after January 1, 1970, two doses of measles-containing vaccine (given as MMR) are recommended. If you already received one dose of MMR vaccine at 12 months of age, you require a second dose of MMR as an adult.\nIn BC, many health professions are authorized to immunize including nurses, nurse practitioners, pharmacists, physicians, and naturopathic doctors. Contact the clinic of your choice to inquire if they provide immunizations. In BC, all health units provide immunizations. Use the health unit finder.\nImmunization Nurse\n",
    "Master Question": "Looking at my old records, I've had 1 dose of the MMR vaccine when I was 1 year old. As an adult, should I now get 2 doses or just 1?\n",
    "Master Question variation 0": "what is the difference between 2 vaccine doses",
    "Master Question variation 1": "should 2 vaccinations be double?",
    "Master Question variation 2": "do you get two vaccine doses of vaccine",
    "Other -condition, symptom etc": "",
    "Subject - Person": "Unknown ",
    "Subject 1 - Immunization": "Immunization Required",
    "Subject 2 - Vaccination / General": "Vaccination",
    "Vaccine 1": "-",
    "Vaccine 2": "",
    "Who is writing this": "adult"
}