{
    "Disease 1": "",
    "Disease 2": "",
    "Keyword": "",
    "Master Answer": "In BC, you do not need a doctor's referral to get your child immunized. Find a health unit near you here and book an immunization appointment.\nImmunization Nurse\n",
    "Master Question": "I don't have a family doctor, do I need a family doctor's referral to get my child immunized or I can just make an appointment with the public health unit?\n",
    "Master Question variation 0": "do i need family doctors referral",
    "Master Question variation 1": "will a GP referral help me get a child immunized",
    "Other -condition, symptom etc": "",
    "Subject - Person": "Child",
    "Subject 1 - Immunization": "Immunization Schedule",
    "Subject 2 - Vaccination / General": "Vaccination",
    "Vaccine 1": "General vaccine safety information",
    "Vaccine 2": "",
    "Who is writing this": "Parent"
}