{
    "Disease 1": "",
    "Disease 2": "",
    "Keyword": "",
    "Master Answer": "We recommend that you contact your local health unit or vaccine provider to discuss what specific brands are used as they may vary from location to location. Your vaccine provider can address any questions you may have about the products. You can find the number for your local health unit here.\nImmunization Nurse\n",
    "Master Question": "Could you please tell me what brands are used for each vaccine on the schedule? Are these the same brands used at all public health units? Are there options for each vaccine?\n",
    "Master Question variation 0": "what brands are used for each vaccine vaccine on the schedule?",
    "Master Question variation 1": "why is there different brands of vaccines for each vaccine?",
    "Other -condition, symptom etc": "brands",
    "Subject - Person": "",
    "Subject 1 - Immunization": "Immunization Schedule",
    "Subject 2 - Vaccination / General": "Vaccination",
    "Vaccine 1": "",
    "Vaccine 2": "",
    "Who is writing this": "Unknown "
}