{
    "Disease 1": "",
    "Disease 2": "",
    "Keyword": "",
    "Master Answer": "In BC, the routine immunization schedule does not include arbovirus vaccines. Arboviruses are group of viruses that are transmitted by mosquitoes, ticks, or other arthropods. Some of these infections have vaccines, such as Yellow Fever or Japanese Encephalitis. Talk to your health care provider or\u00a0travel health clinic\u00a0for more information.\nImmunization Nurse\n",
    "Master Question": "I was recently asked if we immunize annually against arboviruses here in BC. Do we? Or are these infections too rare here?\n",
    "Master Question variation 0": "do we immunize annually against arboviruses",
    "Master Question variation 1": "do we immunize annually against arboviruses here in bc",
    "Other -condition, symptom etc": "Arbovirus",
    "Subject - Person": "Unknown ",
    "Subject 1 - Immunization": "Immunization",
    "Subject 2 - Vaccination / General": "Vaccination",
    "Vaccine 1": "General vaccine safety information",
    "Vaccine 2": "",
    "Who is writing this": "Unknown "
}